{
  "packageId": "core_foundation",
  "metadata": {
    "name": "Core Foundation - Tutorial POC",
    "timestamp": "2025-10-21T00:00:00Z",
    "description": "Tutorial: Evening arrival at Brass Bell Inn, work for shelter",
    "author": "Wayfarer Team",
    "version": "6.0.0"
  },
  "content": {
    "venues": [
      {
        "id": "brass_bell_inn",
        "name": "The Brass Bell Inn",
        "description": "A warm inn where lamplight spills from windows. Inside: warmth, food, safety. The common room hums with evening conversations.",
        "districtId": "town_center",
        "tier": 1,
        "locationType": "Urban"
      },
      {
        "id": "town_square",
        "name": "Town Square",
        "description": "The heart of the town, where traders gather and townsfolk meet. The Brass Bell Inn beckons from across the square.",
        "districtId": "town_center",
        "tier": 1,
        "locationType": "Urban"
      }
    ],
    "locations": [
      {
        "id": "square_center",
        "venueId": "town_square",
        "name": "Town Square Center",
        "description": "You've been walking since dawn. Your legs ache, your coin purse feels light, and the sun is setting. The warm glow of The Brass Bell Inn beckons from across the square.",
        "properties": {
          "base": [
            "crossroads"
          ],
          "all": [
            "public",
            "busy"
          ]
        },
        "canInvestigate": false
      },
      {
        "id": "common_room",
        "venueId": "brass_bell_inn",
        "name": "Common Room",
        "description": "Lamplight spills from windows. Inside: warmth, food, safety. The common room hums with evening conversations. Elena, the innkeeper, wipes down tables while watching travelers settle in for the night.",
        "properties": {
          "base": [
            "crossroads",
            "commercial"
          ],
          "all": [
            "public",
            "busy",
            "restful",
            "lodging"
          ]
        },
        "canInvestigate": false
      },
      {
        "id": "upstairs_room",
        "venueId": "brass_bell_inn",
        "name": "Upstairs Room",
        "description": "A simple guest room. Quiet, safe. A bed waits.",
        "properties": {
          "base": [
            "lodging"
          ],
          "all": [
            "restful",
            "lodging"
          ]
        },
        "canInvestigate": false
      },
      {
        "id": "fountain_plaza",
        "venueId": "town_square",
        "name": "Fountain Plaza",
        "description": "The town fountain. Locals gather here to chat and trade news. A courier's board posts delivery opportunities.",
        "properties": {
          "base": [
            "public",
            "commercial"
          ],
          "all": [
            "public",
            "busy"
          ]
        },
        "canInvestigate": false
      }
    ]
  }
}
